CHANGES.txt
LICENSE.txt
MANIFEST.in
README.md
setup.py
js/__init__.py
js.jasny_bootstrap.egg-info/PKG-INFO
js.jasny_bootstrap.egg-info/SOURCES.txt
js.jasny_bootstrap.egg-info/dependency_links.txt
js.jasny_bootstrap.egg-info/entry_points.txt
js.jasny_bootstrap.egg-info/namespace_packages.txt
js.jasny_bootstrap.egg-info/not-zip-safe
js.jasny_bootstrap.egg-info/requires.txt
js.jasny_bootstrap.egg-info/top_level.txt
js/jasny_bootstrap/__init__.py
js/jasny_bootstrap/test_jasny_bootstrap.txt
js/jasny_bootstrap/resources/css/jasny-bootstrap.css
js/jasny_bootstrap/resources/js/jasny-bootstrap.js
js/jasny_bootstrap/resources/js/jasny-bootstrap.min.js