Metadata-Version: 1.0
Name: js.jasny-bootstrap
Version: 3.1.3.post1
Summary: Fanstatic packaging of Jasny Bootstrap
Home-page: UNKNOWN
Author: Fanstatic Developers
Author-email: fanstatic@googlegroups.com
License: BSD
Platform: UNKNOWN
